{
  "nightly": {
    "description": "Pre-releases",
    "hide": false,
    "last_updated": "2025-03-31T23:33:38.000Z",
    "last_updated_url": "https://github.com/hotio/bazarr/actions/runs/14183383906",
    "latest": false,
    "tags": [
      "nightly",
      "nightly-1.5.2-beta.31",
      "nightly-aeb67bb"
    ]
  },
  "release": {
    "description": "Releases",
    "hide": false,
    "last_updated": "2025-04-01T02:21:43.000Z",
    "last_updated_url": "https://github.com/hotio/bazarr/actions/runs/14185573700",
    "latest": true,
    "tags": [
      "release",
      "release-1.5.1",
      "release-88ac003"
    ]
  }
}
