{
  "nightly": {
    "description": "Pre-releases",
    "hide": false,
    "last_updated": "2024-04-23T04:53:19.000Z",
    "last_updated_url": "https://github.com/hotio/bazarr/actions/runs/8794922411",
    "latest": false,
    "tags": [
      "nightly",
      "nightly-1.4.3-beta.24",
      "nightly-3e8f5ed"
    ]
  },
  "release": {
    "description": "Releases",
    "hide": false,
    "last_updated": "2024-04-23T09:22:54.000Z",
    "last_updated_url": "https://github.com/hotio/bazarr/actions/runs/8797815903",
    "latest": true,
    "tags": [
      "release",
      "release-1.4.2",
      "release-510be0a"
    ]
  }
}
